{
  "teams": [
    {
      "teamId": "MEX",
      "name": "Mexico",
      "code": "MEX",
      "groupId": "A",
      "pWinGroup": 1,
      "pAdvanceGroup": 1,
      "pReachR16": 1,
      "pReachQF": 0,
      "pReachSF": 0,
      "pReachFinal": 0,
      "pChampion": 0,
      "pChampionModel": 0,
      "pChampionInitial": 0.024
    },
    {
      "teamId": "RSA",
      "name": "South Africa",
      "code": "RSA",
      "groupId": "A",
      "pWinGroup": 0,
      "pAdvanceGroup": 1,
      "pReachR16": 0,
      "pReachQF": 0,
      "pReachSF": 0,
      "pReachFinal": 0,
      "pChampion": 0,
      "pChampionModel": 0,
      "pChampionInitial": 0.0004
    },
    {
      "teamId": "KOR",
      "name": "South Korea",
      "code": "KOR",
      "groupId": "A",
      "pWinGroup": 0,
      "pAdvanceGroup": 0,
      "pReachR16": 0,
      "pReachQF": 0,
      "pReachSF": 0,
      "pReachFinal": 0,
      "pChampion": 0,
      "pChampionModel": 0,
      "pChampionInitial": 0.007
    },
    {
      "teamId": "CZE",
      "name": "Czechia",
      "code": "CZE",
      "groupId": "A",
      "pWinGroup": 0,
      "pAdvanceGroup": 0,
      "pReachR16": 0,
      "pReachQF": 0,
      "pReachSF": 0,
      "pReachFinal": 0,
      "pChampion": 0,
      "pChampionModel": 0,
      "pChampionInitial": 0.0018
    },
    {
      "teamId": "CAN",
      "name": "Canada",
      "code": "CAN",
      "groupId": "B",
      "pWinGroup": 0,
      "pAdvanceGroup": 1,
      "pReachR16": 1,
      "pReachQF": 0.29536,
      "pReachSF": 0.069,
      "pReachFinal": 0.01084,
      "pChampion": 0.0026,
      "pChampionModel": 0.0026,
      "pChampionInitial": 0.0068
    },
    {
      "teamId": "BIH",
      "name": "Bosnia-Herzegovina",
      "code": "BIH",
      "groupId": "B",
      "pWinGroup": 0,
      "pAdvanceGroup": 1,
      "pReachR16": 0,
      "pReachQF": 0,
      "pReachSF": 0,
      "pReachFinal": 0,
      "pChampion": 0,
      "pChampionModel": 0,
      "pChampionInitial": 0.0004
    },
    {
      "teamId": "QAT",
      "name": "Qatar",
      "code": "QAT",
      "groupId": "B",
      "pWinGroup": 0,
      "pAdvanceGroup": 0,
      "pReachR16": 0,
      "pReachQF": 0,
      "pReachSF": 0,
      "pReachFinal": 0,
      "pChampion": 0,
      "pChampionModel": 0,
      "pChampionInitial": 0.0018
    },
    {
      "teamId": "SUI",
      "name": "Switzerland",
      "code": "SUI",
      "groupId": "B",
      "pWinGroup": 1,
      "pAdvanceGroup": 1,
      "pReachR16": 1,
      "pReachQF": 1,
      "pReachSF": 0.11204,
      "pReachFinal": 0.03356,
      "pChampion": 0.0091,
      "pChampionModel": 0.0091,
      "pChampionInitial": 0.0156
    },
    {
      "teamId": "BRA",
      "name": "Brazil",
      "code": "BRA",
      "groupId": "C",
      "pWinGroup": 1,
      "pAdvanceGroup": 1,
      "pReachR16": 1,
      "pReachQF": 0,
      "pReachSF": 0,
      "pReachFinal": 0,
      "pChampion": 0,
      "pChampionModel": 0,
      "pChampionInitial": 0.0532
    },
    {
      "teamId": "MAR",
      "name": "Morocco",
      "code": "MAR",
      "groupId": "C",
      "pWinGroup": 0,
      "pAdvanceGroup": 1,
      "pReachR16": 0,
      "pReachQF": 0,
      "pReachSF": 0,
      "pReachFinal": 0,
      "pChampion": 0,
      "pChampionModel": 0,
      "pChampionInitial": 0.043
    },
    {
      "teamId": "HAI",
      "name": "Haiti",
      "code": "HAI",
      "groupId": "C",
      "pWinGroup": 0,
      "pAdvanceGroup": 0,
      "pReachR16": 0,
      "pReachQF": 0,
      "pReachSF": 0,
      "pReachFinal": 0,
      "pChampion": 0,
      "pChampionModel": 0,
      "pChampionInitial": 0
    },
    {
      "teamId": "SCO",
      "name": "Scotland",
      "code": "SCO",
      "groupId": "C",
      "pWinGroup": 0,
      "pAdvanceGroup": 0,
      "pReachR16": 0,
      "pReachQF": 0,
      "pReachSF": 0,
      "pReachFinal": 0,
      "pChampion": 0,
      "pChampionModel": 0,
      "pChampionInitial": 0.0014
    },
    {
      "teamId": "USA",
      "name": "United States",
      "code": "USA",
      "groupId": "D",
      "pWinGroup": 1,
      "pAdvanceGroup": 1,
      "pReachR16": 1,
      "pReachQF": 0,
      "pReachSF": 0,
      "pReachFinal": 0,
      "pChampion": 0,
      "pChampionModel": 0,
      "pChampionInitial": 0.0198
    },
    {
      "teamId": "PAR",
      "name": "Paraguay",
      "code": "PAR",
      "groupId": "D",
      "pWinGroup": 0,
      "pAdvanceGroup": 1,
      "pReachR16": 0,
      "pReachQF": 0,
      "pReachSF": 0,
      "pReachFinal": 0,
      "pChampion": 0,
      "pChampionModel": 0,
      "pChampionInitial": 0.0022
    },
    {
      "teamId": "AUS",
      "name": "Australia",
      "code": "AUS",
      "groupId": "D",
      "pWinGroup": 0,
      "pAdvanceGroup": 1,
      "pReachR16": 1,
      "pReachQF": 0.18236,
      "pReachSF": 0.07032,
      "pReachFinal": 0.01564,
      "pChampion": 0.00286,
      "pChampionModel": 0.00286,
      "pChampionInitial": 0.0048
    },
    {
      "teamId": "TUR",
      "name": "Türkiye",
      "code": "TUR",
      "groupId": "D",
      "pWinGroup": 0,
      "pAdvanceGroup": 0,
      "pReachR16": 0,
      "pReachQF": 0,
      "pReachSF": 0,
      "pReachFinal": 0,
      "pChampion": 0,
      "pChampionModel": 0,
      "pChampionInitial": 0.0066
    },
    {
      "teamId": "GER",
      "name": "Germany",
      "code": "GER",
      "groupId": "E",
      "pWinGroup": 1,
      "pAdvanceGroup": 1,
      "pReachR16": 1,
      "pReachQF": 0.3042,
      "pReachSF": 0.15102,
      "pReachFinal": 0.04006,
      "pChampion": 0.01354,
      "pChampionModel": 0.01354,
      "pChampionInitial": 0.0348
    },
    {
      "teamId": "CUW",
      "name": "Curaçao",
      "code": "CUW",
      "groupId": "E",
      "pWinGroup": 0,
      "pAdvanceGroup": 0,
      "pReachR16": 0,
      "pReachQF": 0,
      "pReachSF": 0,
      "pReachFinal": 0,
      "pChampion": 0,
      "pChampionModel": 0,
      "pChampionInitial": 0
    },
    {
      "teamId": "CIV",
      "name": "Ivory Coast",
      "code": "CIV",
      "groupId": "E",
      "pWinGroup": 0,
      "pAdvanceGroup": 1,
      "pReachR16": 0,
      "pReachQF": 0,
      "pReachSF": 0,
      "pReachFinal": 0,
      "pChampion": 0,
      "pChampionModel": 0,
      "pChampionInitial": 0.0026
    },
    {
      "teamId": "ECU",
      "name": "Ecuador",
      "code": "ECU",
      "groupId": "E",
      "pWinGroup": 0,
      "pAdvanceGroup": 1,
      "pReachR16": 0,
      "pReachQF": 0,
      "pReachSF": 0,
      "pReachFinal": 0,
      "pChampion": 0,
      "pChampionModel": 0,
      "pChampionInitial": 0.006
    },
    {
      "teamId": "NED",
      "name": "Netherlands",
      "code": "NED",
      "groupId": "F",
      "pWinGroup": 1,
      "pAdvanceGroup": 1,
      "pReachR16": 1,
      "pReachQF": 0.70464,
      "pReachSF": 0.29768,
      "pReachFinal": 0.09242,
      "pChampion": 0.03698,
      "pChampionModel": 0.03698,
      "pChampionInitial": 0.0406
    },
    {
      "teamId": "JPN",
      "name": "Japan",
      "code": "JPN",
      "groupId": "F",
      "pWinGroup": 0,
      "pAdvanceGroup": 1,
      "pReachR16": 0,
      "pReachQF": 0,
      "pReachSF": 0,
      "pReachFinal": 0,
      "pChampion": 0,
      "pChampionModel": 0,
      "pChampionInitial": 0.0154
    },
    {
      "teamId": "SWE",
      "name": "Sweden",
      "code": "SWE",
      "groupId": "F",
      "pWinGroup": 0,
      "pAdvanceGroup": 1,
      "pReachR16": 0,
      "pReachQF": 0,
      "pReachSF": 0,
      "pReachFinal": 0,
      "pChampion": 0,
      "pChampionModel": 0,
      "pChampionInitial": 0.0038
    },
    {
      "teamId": "TUN",
      "name": "Tunisia",
      "code": "TUN",
      "groupId": "F",
      "pWinGroup": 0,
      "pAdvanceGroup": 0,
      "pReachR16": 0,
      "pReachQF": 0,
      "pReachSF": 0,
      "pReachFinal": 0,
      "pChampion": 0,
      "pChampionModel": 0,
      "pChampionInitial": 0.0006
    },
    {
      "teamId": "BEL",
      "name": "Belgium",
      "code": "BEL",
      "groupId": "G",
      "pWinGroup": 1,
      "pAdvanceGroup": 1,
      "pReachR16": 1,
      "pReachQF": 1,
      "pReachSF": 0,
      "pReachFinal": 0,
      "pChampion": 0,
      "pChampionModel": 0,
      "pChampionInitial": 0.0456
    },
    {
      "teamId": "EGY",
      "name": "Egypt",
      "code": "EGY",
      "groupId": "G",
      "pWinGroup": 0,
      "pAdvanceGroup": 1,
      "pReachR16": 0,
      "pReachQF": 0,
      "pReachSF": 0,
      "pReachFinal": 0,
      "pChampion": 0,
      "pChampionModel": 0,
      "pChampionInitial": 0.0074
    },
    {
      "teamId": "IRN",
      "name": "Iran",
      "code": "IRN",
      "groupId": "G",
      "pWinGroup": 0,
      "pAdvanceGroup": 0,
      "pReachR16": 0,
      "pReachQF": 0,
      "pReachSF": 0,
      "pReachFinal": 0,
      "pChampion": 0,
      "pChampionModel": 0,
      "pChampionInitial": 0.0154
    },
    {
      "teamId": "NZL",
      "name": "New Zealand",
      "code": "NZL",
      "groupId": "G",
      "pWinGroup": 0,
      "pAdvanceGroup": 0,
      "pReachR16": 0,
      "pReachQF": 0,
      "pReachSF": 0,
      "pReachFinal": 0,
      "pChampion": 0,
      "pChampionModel": 0,
      "pChampionInitial": 0
    },
    {
      "teamId": "ESP",
      "name": "Spain",
      "code": "ESP",
      "groupId": "H",
      "pWinGroup": 1,
      "pAdvanceGroup": 1,
      "pReachR16": 1,
      "pReachQF": 1,
      "pReachSF": 1,
      "pReachFinal": 0.85668,
      "pChampion": 0.5217425449039023,
      "pChampionModel": 0.50036,
      "pChampionMarket": 0.5716351496796743,
      "pChampionInitial": 0.26207054490390225
    },
    {
      "teamId": "CPV",
      "name": "Cape Verde",
      "code": "CPV",
      "groupId": "H",
      "pWinGroup": 0,
      "pAdvanceGroup": 1,
      "pReachR16": 0,
      "pReachQF": 0,
      "pReachSF": 0,
      "pReachFinal": 0,
      "pChampion": 0,
      "pChampionModel": 0,
      "pChampionInitial": 0
    },
    {
      "teamId": "KSA",
      "name": "Saudi Arabia",
      "code": "KSA",
      "groupId": "H",
      "pWinGroup": 0,
      "pAdvanceGroup": 0,
      "pReachR16": 0,
      "pReachQF": 0,
      "pReachSF": 0,
      "pReachFinal": 0,
      "pChampion": 0,
      "pChampionModel": 0,
      "pChampionInitial": 0.0006
    },
    {
      "teamId": "URU",
      "name": "Uruguay",
      "code": "URU",
      "groupId": "H",
      "pWinGroup": 0,
      "pAdvanceGroup": 0,
      "pReachR16": 0,
      "pReachQF": 0,
      "pReachSF": 0,
      "pReachFinal": 0,
      "pChampion": 0,
      "pChampionModel": 0,
      "pChampionInitial": 0.0192
    },
    {
      "teamId": "FRA",
      "name": "France",
      "code": "FRA",
      "groupId": "I",
      "pWinGroup": 1,
      "pAdvanceGroup": 1,
      "pReachR16": 1,
      "pReachQF": 0.6958,
      "pReachSF": 0.4823,
      "pReachFinal": 0,
      "pChampion": 0,
      "pChampionModel": 0,
      "pChampionInitial": 0.1234
    },
    {
      "teamId": "SEN",
      "name": "Senegal",
      "code": "SEN",
      "groupId": "I",
      "pWinGroup": 0,
      "pAdvanceGroup": 1,
      "pReachR16": 0,
      "pReachQF": 0,
      "pReachSF": 0,
      "pReachFinal": 0,
      "pChampion": 0,
      "pChampionModel": 0,
      "pChampionInitial": 0.0236
    },
    {
      "teamId": "IRQ",
      "name": "Iraq",
      "code": "IRQ",
      "groupId": "I",
      "pWinGroup": 0,
      "pAdvanceGroup": 0,
      "pReachR16": 0,
      "pReachQF": 0,
      "pReachSF": 0,
      "pReachFinal": 0,
      "pChampion": 0,
      "pChampionModel": 0,
      "pChampionInitial": 0
    },
    {
      "teamId": "NOR",
      "name": "Norway",
      "code": "NOR",
      "groupId": "I",
      "pWinGroup": 0,
      "pAdvanceGroup": 1,
      "pReachR16": 1,
      "pReachQF": 1,
      "pReachSF": 0,
      "pReachFinal": 0,
      "pChampion": 0,
      "pChampionModel": 0,
      "pChampionInitial": 0.0036
    },
    {
      "teamId": "ARG",
      "name": "Argentina",
      "code": "ARG",
      "groupId": "J",
      "pWinGroup": 1,
      "pAdvanceGroup": 1,
      "pReachR16": 1,
      "pReachQF": 0.81764,
      "pReachSF": 0.81764,
      "pReachFinal": 0,
      "pChampion": 0.057871489652366014,
      "pChampionModel": 0,
      "pChampionMarket": 0.19290496550788672,
      "pChampionInitial": 0.149151489652366
    },
    {
      "teamId": "ALG",
      "name": "Algeria",
      "code": "ALG",
      "groupId": "J",
      "pWinGroup": 0,
      "pAdvanceGroup": 1,
      "pReachR16": 0,
      "pReachQF": 0,
      "pReachSF": 0,
      "pReachFinal": 0,
      "pChampion": 0,
      "pChampionModel": 0,
      "pChampionInitial": 0.0042
    },
    {
      "teamId": "AUT",
      "name": "Austria",
      "code": "AUT",
      "groupId": "J",
      "pWinGroup": 0,
      "pAdvanceGroup": 1,
      "pReachR16": 0,
      "pReachQF": 0,
      "pReachSF": 0,
      "pReachFinal": 0,
      "pChampion": 0,
      "pChampionModel": 0,
      "pChampionInitial": 0.0052
    },
    {
      "teamId": "JOR",
      "name": "Jordan",
      "code": "JOR",
      "groupId": "J",
      "pWinGroup": 0,
      "pAdvanceGroup": 0,
      "pReachR16": 0,
      "pReachQF": 0,
      "pReachSF": 0,
      "pReachFinal": 0,
      "pChampion": 0,
      "pChampionModel": 0,
      "pChampionInitial": 0.0002
    },
    {
      "teamId": "POR",
      "name": "Portugal",
      "code": "POR",
      "groupId": "K",
      "pWinGroup": 0,
      "pAdvanceGroup": 1,
      "pReachR16": 1,
      "pReachQF": 0,
      "pReachSF": 0,
      "pReachFinal": 0,
      "pChampion": 0,
      "pChampionModel": 0,
      "pChampionInitial": 0.0482
    },
    {
      "teamId": "COD",
      "name": "Congo DR",
      "code": "COD",
      "groupId": "K",
      "pWinGroup": 0,
      "pAdvanceGroup": 1,
      "pReachR16": 0,
      "pReachQF": 0,
      "pReachSF": 0,
      "pReachFinal": 0,
      "pChampion": 0,
      "pChampionModel": 0,
      "pChampionInitial": 0.0008
    },
    {
      "teamId": "UZB",
      "name": "Uzbekistan",
      "code": "UZB",
      "groupId": "K",
      "pWinGroup": 0,
      "pAdvanceGroup": 0,
      "pReachR16": 0,
      "pReachQF": 0,
      "pReachSF": 0,
      "pReachFinal": 0,
      "pChampion": 0,
      "pChampionModel": 0,
      "pChampionInitial": 0.0012
    },
    {
      "teamId": "COL",
      "name": "Colombia",
      "code": "COL",
      "groupId": "K",
      "pWinGroup": 1,
      "pAdvanceGroup": 1,
      "pReachR16": 1,
      "pReachQF": 0,
      "pReachSF": 0,
      "pReachFinal": 0,
      "pChampion": 0,
      "pChampionModel": 0,
      "pChampionInitial": 0.0258
    },
    {
      "teamId": "ENG",
      "name": "England",
      "code": "ENG",
      "groupId": "L",
      "pWinGroup": 1,
      "pAdvanceGroup": 1,
      "pReachR16": 1,
      "pReachQF": 1,
      "pReachSF": 1,
      "pReachFinal": 0.9508,
      "pChampion": 0.37482996544373165,
      "pChampionModel": 0.43456,
      "pChampionMarket": 0.23545988481243899,
      "pChampionInitial": 0.13405796544373166
    },
    {
      "teamId": "CRO",
      "name": "Croatia",
      "code": "CRO",
      "groupId": "L",
      "pWinGroup": 0,
      "pAdvanceGroup": 1,
      "pReachR16": 0,
      "pReachQF": 0,
      "pReachSF": 0,
      "pReachFinal": 0,
      "pChampion": 0,
      "pChampionModel": 0,
      "pChampionInitial": 0.0292
    },
    {
      "teamId": "GHA",
      "name": "Ghana",
      "code": "GHA",
      "groupId": "L",
      "pWinGroup": 0,
      "pAdvanceGroup": 1,
      "pReachR16": 0,
      "pReachQF": 0,
      "pReachSF": 0,
      "pReachFinal": 0,
      "pChampion": 0,
      "pChampionModel": 0,
      "pChampionInitial": 0
    },
    {
      "teamId": "PAN",
      "name": "Panama",
      "code": "PAN",
      "groupId": "L",
      "pWinGroup": 0,
      "pAdvanceGroup": 0,
      "pReachR16": 0,
      "pReachQF": 0,
      "pReachSF": 0,
      "pReachFinal": 0,
      "pChampion": 0,
      "pChampionModel": 0,
      "pChampionInitial": 0.0034
    }
  ],
  "championDistribution": {
    "CAN": 0.0026,
    "SUI": 0.0091,
    "AUS": 0.00286,
    "GER": 0.01354,
    "NED": 0.03698,
    "ESP": 0.50036,
    "ENG": 0.43456
  },
  "modelConfig": {
    "type": "poisson",
    "baseGoalsRate": 1.25,
    "blendOddsWeight": 0.3,
    "knockoutGoalsMultiplier": 0.85,
    "formVolatility": 0.05,
    "eloRegressionFactor": 1
  },
  "simCount": 50000,
  "seed": 1733930763,
  "generatedAt": "2026-07-15T19:56:04.396Z",
  "dataSnapshotTimestamp": "2026-07-15T19:55:58.835Z"
}