{
  "teams": [
    {
      "teamId": "MEX",
      "name": "Mexico",
      "code": "MEX",
      "groupId": "A",
      "pWinGroup": 1,
      "pAdvanceGroup": 1,
      "pReachR16": 1,
      "pReachQF": 0.3975,
      "pReachSF": 0.19834,
      "pReachFinal": 0.0926,
      "pChampion": 0.03628683365986864,
      "pChampionModel": 0.03826,
      "pChampionMarket": 0.03168277886622882,
      "pChampionInitial": 0.024904833659868644
    },
    {
      "teamId": "RSA",
      "name": "South Africa",
      "code": "RSA",
      "groupId": "A",
      "pWinGroup": 0,
      "pAdvanceGroup": 1,
      "pReachR16": 0,
      "pReachQF": 0,
      "pReachSF": 0,
      "pReachFinal": 0,
      "pChampion": 0,
      "pChampionModel": 0,
      "pChampionInitial": 0
    },
    {
      "teamId": "KOR",
      "name": "South Korea",
      "code": "KOR",
      "groupId": "A",
      "pWinGroup": 0,
      "pAdvanceGroup": 0,
      "pReachR16": 0,
      "pReachQF": 0,
      "pReachSF": 0,
      "pReachFinal": 0,
      "pChampion": 0,
      "pChampionModel": 0,
      "pChampionInitial": 0.007
    },
    {
      "teamId": "CZE",
      "name": "Czechia",
      "code": "CZE",
      "groupId": "A",
      "pWinGroup": 0,
      "pAdvanceGroup": 0,
      "pReachR16": 0,
      "pReachQF": 0,
      "pReachSF": 0,
      "pReachFinal": 0,
      "pChampion": 0,
      "pChampionModel": 0,
      "pChampionInitial": 0.002
    },
    {
      "teamId": "CAN",
      "name": "Canada",
      "code": "CAN",
      "groupId": "B",
      "pWinGroup": 0,
      "pAdvanceGroup": 1,
      "pReachR16": 1,
      "pReachQF": 0.31136,
      "pReachSF": 0.07656,
      "pReachFinal": 0.02208,
      "pChampion": 0.0055196462206029235,
      "pChampionModel": 0.00666,
      "pChampionMarket": 0.002858820735343081,
      "pChampionInitial": 0.005197646220602923
    },
    {
      "teamId": "BIH",
      "name": "Bosnia-Herzegovina",
      "code": "BIH",
      "groupId": "B",
      "pWinGroup": 0,
      "pAdvanceGroup": 1,
      "pReachR16": 0,
      "pReachQF": 0,
      "pReachSF": 0,
      "pReachFinal": 0,
      "pChampion": 0,
      "pChampionModel": 0,
      "pChampionInitial": 0
    },
    {
      "teamId": "QAT",
      "name": "Qatar",
      "code": "QAT",
      "groupId": "B",
      "pWinGroup": 0,
      "pAdvanceGroup": 0,
      "pReachR16": 0,
      "pReachQF": 0,
      "pReachSF": 0,
      "pReachFinal": 0,
      "pChampion": 0,
      "pChampionModel": 0,
      "pChampionInitial": 0.0008
    },
    {
      "teamId": "SUI",
      "name": "Switzerland",
      "code": "SUI",
      "groupId": "B",
      "pWinGroup": 1,
      "pAdvanceGroup": 1,
      "pReachR16": 0.65178,
      "pReachQF": 0.3205,
      "pReachSF": 0.11688,
      "pReachFinal": 0.04386,
      "pChampion": 0.013754319980036333,
      "pChampionModel": 0.016,
      "pChampionMarket": 0.008514399933454445,
      "pChampionInitial": 0.014454319980036334
    },
    {
      "teamId": "BRA",
      "name": "Brazil",
      "code": "BRA",
      "groupId": "C",
      "pWinGroup": 1,
      "pAdvanceGroup": 1,
      "pReachR16": 1,
      "pReachQF": 0.719,
      "pReachSF": 0.35242,
      "pReachFinal": 0.18076,
      "pChampion": 0.08241390834362143,
      "pChampionModel": 0.08782,
      "pChampionMarket": 0.06979969447873814,
      "pChampionInitial": 0.05859990834362144
    },
    {
      "teamId": "MAR",
      "name": "Morocco",
      "code": "MAR",
      "groupId": "C",
      "pWinGroup": 0,
      "pAdvanceGroup": 1,
      "pReachR16": 0,
      "pReachQF": 0,
      "pReachSF": 0,
      "pReachFinal": 0,
      "pChampion": 0.008043343709485926,
      "pChampionModel": 0,
      "pChampionMarket": 0.026811145698286423,
      "pChampionInitial": 0.04038334370948592
    },
    {
      "teamId": "HAI",
      "name": "Haiti",
      "code": "HAI",
      "groupId": "C",
      "pWinGroup": 0,
      "pAdvanceGroup": 0,
      "pReachR16": 0,
      "pReachQF": 0,
      "pReachSF": 0,
      "pReachFinal": 0,
      "pChampion": 0,
      "pChampionModel": 0,
      "pChampionInitial": 0
    },
    {
      "teamId": "SCO",
      "name": "Scotland",
      "code": "SCO",
      "groupId": "C",
      "pWinGroup": 0,
      "pAdvanceGroup": 0,
      "pReachR16": 0,
      "pReachQF": 0,
      "pReachSF": 0,
      "pReachFinal": 0,
      "pChampion": 0,
      "pChampionModel": 0,
      "pChampionInitial": 0.0016
    },
    {
      "teamId": "USA",
      "name": "United States",
      "code": "USA",
      "groupId": "D",
      "pWinGroup": 1,
      "pAdvanceGroup": 1,
      "pReachR16": 1,
      "pReachQF": 0.43904,
      "pReachSF": 0.15318,
      "pReachFinal": 0.05718,
      "pChampion": 0.023822872813847627,
      "pChampionModel": 0.02184,
      "pChampionMarket": 0.02844957604615876,
      "pChampionInitial": 0.02127487281384763
    },
    {
      "teamId": "PAR",
      "name": "Paraguay",
      "code": "PAR",
      "groupId": "D",
      "pWinGroup": 0,
      "pAdvanceGroup": 1,
      "pReachR16": 0,
      "pReachQF": 0,
      "pReachSF": 0,
      "pReachFinal": 0,
      "pChampion": 0.0005853965715108614,
      "pChampionModel": 0,
      "pChampionMarket": 0.0019513219050362048,
      "pChampionInitial": 0.0018453965715108612
    },
    {
      "teamId": "AUS",
      "name": "Australia",
      "code": "AUS",
      "groupId": "D",
      "pWinGroup": 0,
      "pAdvanceGroup": 1,
      "pReachR16": 0.47348,
      "pReachQF": 0.10636,
      "pReachSF": 0.04266,
      "pReachFinal": 0.01256,
      "pChampion": 0.0030182351056088257,
      "pChampionModel": 0.0035,
      "pChampionMarket": 0.0018941170186960864,
      "pChampionInitial": 0.004348235105608826
    },
    {
      "teamId": "TUR",
      "name": "Türkiye",
      "code": "TUR",
      "groupId": "D",
      "pWinGroup": 0,
      "pAdvanceGroup": 0,
      "pReachR16": 0,
      "pReachQF": 0,
      "pReachSF": 0,
      "pReachFinal": 0,
      "pChampion": 0,
      "pChampionModel": 0,
      "pChampionInitial": 0.0084
    },
    {
      "teamId": "GER",
      "name": "Germany",
      "code": "GER",
      "groupId": "E",
      "pWinGroup": 1,
      "pAdvanceGroup": 1,
      "pReachR16": 1,
      "pReachQF": 0.30714,
      "pReachSF": 0.1555,
      "pReachFinal": 0.06384,
      "pChampion": 0.02562,
      "pChampionModel": 0.02562,
      "pChampionInitial": 0.0392
    },
    {
      "teamId": "CUW",
      "name": "Curaçao",
      "code": "CUW",
      "groupId": "E",
      "pWinGroup": 0,
      "pAdvanceGroup": 0,
      "pReachR16": 0,
      "pReachQF": 0,
      "pReachSF": 0,
      "pReachFinal": 0,
      "pChampion": 0,
      "pChampionModel": 0,
      "pChampionInitial": 0
    },
    {
      "teamId": "CIV",
      "name": "Ivory Coast",
      "code": "CIV",
      "groupId": "E",
      "pWinGroup": 0,
      "pAdvanceGroup": 1,
      "pReachR16": 0,
      "pReachQF": 0,
      "pReachSF": 0,
      "pReachFinal": 0,
      "pChampion": 0,
      "pChampionModel": 0,
      "pChampionInitial": 0.0032
    },
    {
      "teamId": "ECU",
      "name": "Ecuador",
      "code": "ECU",
      "groupId": "E",
      "pWinGroup": 0,
      "pAdvanceGroup": 1,
      "pReachR16": 0,
      "pReachQF": 0,
      "pReachSF": 0,
      "pReachFinal": 0,
      "pChampion": 0,
      "pChampionModel": 0,
      "pChampionInitial": 0.009
    },
    {
      "teamId": "NED",
      "name": "Netherlands",
      "code": "NED",
      "groupId": "F",
      "pWinGroup": 1,
      "pAdvanceGroup": 1,
      "pReachR16": 1,
      "pReachQF": 0.68864,
      "pReachSF": 0.28908,
      "pReachFinal": 0.13612,
      "pChampion": 0.06314,
      "pChampionModel": 0.06314,
      "pChampionInitial": 0.044
    },
    {
      "teamId": "JPN",
      "name": "Japan",
      "code": "JPN",
      "groupId": "F",
      "pWinGroup": 0,
      "pAdvanceGroup": 1,
      "pReachR16": 0,
      "pReachQF": 0,
      "pReachSF": 0,
      "pReachFinal": 0,
      "pChampion": 0,
      "pChampionModel": 0,
      "pChampionInitial": 0.014
    },
    {
      "teamId": "SWE",
      "name": "Sweden",
      "code": "SWE",
      "groupId": "F",
      "pWinGroup": 0,
      "pAdvanceGroup": 1,
      "pReachR16": 0,
      "pReachQF": 0,
      "pReachSF": 0,
      "pReachFinal": 0,
      "pChampion": 0,
      "pChampionModel": 0,
      "pChampionInitial": 0.0012
    },
    {
      "teamId": "TUN",
      "name": "Tunisia",
      "code": "TUN",
      "groupId": "F",
      "pWinGroup": 0,
      "pAdvanceGroup": 0,
      "pReachR16": 0,
      "pReachQF": 0,
      "pReachSF": 0,
      "pReachFinal": 0,
      "pChampion": 0,
      "pChampionModel": 0,
      "pChampionInitial": 0.0006
    },
    {
      "teamId": "BEL",
      "name": "Belgium",
      "code": "BEL",
      "groupId": "G",
      "pWinGroup": 1,
      "pAdvanceGroup": 1,
      "pReachR16": 1,
      "pReachQF": 0.56096,
      "pReachSF": 0.2349,
      "pReachFinal": 0.10264,
      "pChampion": 0.03681399136110539,
      "pChampionModel": 0.04576,
      "pChampionMarket": 0.015939971203684643,
      "pChampionInitial": 0.03684199136110539
    },
    {
      "teamId": "EGY",
      "name": "Egypt",
      "code": "EGY",
      "groupId": "G",
      "pWinGroup": 0,
      "pAdvanceGroup": 1,
      "pReachR16": 0.52652,
      "pReachQF": 0.12132,
      "pReachSF": 0.04982,
      "pReachFinal": 0.01546,
      "pChampion": 0.003676633968320109,
      "pChampionModel": 0.00432,
      "pChampionMarket": 0.0021754465610670302,
      "pChampionInitial": 0.004712633968320108
    },
    {
      "teamId": "IRN",
      "name": "Iran",
      "code": "IRN",
      "groupId": "G",
      "pWinGroup": 0,
      "pAdvanceGroup": 0,
      "pReachR16": 0,
      "pReachQF": 0,
      "pReachSF": 0,
      "pReachFinal": 0,
      "pChampion": 0,
      "pChampionModel": 0,
      "pChampionInitial": 0.0106
    },
    {
      "teamId": "NZL",
      "name": "New Zealand",
      "code": "NZL",
      "groupId": "G",
      "pWinGroup": 0,
      "pAdvanceGroup": 0,
      "pReachR16": 0,
      "pReachQF": 0,
      "pReachSF": 0,
      "pReachFinal": 0,
      "pChampion": 0,
      "pChampionModel": 0,
      "pChampionInitial": 0
    },
    {
      "teamId": "ESP",
      "name": "Spain",
      "code": "ESP",
      "groupId": "H",
      "pWinGroup": 1,
      "pAdvanceGroup": 1,
      "pReachR16": 1,
      "pReachQF": 0.6276,
      "pReachSF": 0.41198,
      "pReachFinal": 0.23478,
      "pChampion": 0.13392721432762658,
      "pChampionModel": 0.13408,
      "pChampionMarket": 0.13357071442542195,
      "pChampionInitial": 0.12743121432762658
    },
    {
      "teamId": "CPV",
      "name": "Cape Verde",
      "code": "CPV",
      "groupId": "H",
      "pWinGroup": 0,
      "pAdvanceGroup": 1,
      "pReachR16": 0.0402,
      "pReachQF": 0.01336,
      "pReachSF": 0.00288,
      "pReachFinal": 0.00048,
      "pChampion": 0.0003014196348515485,
      "pChampionModel": 0.00004,
      "pChampionMarket": 0.0009113987828384951,
      "pChampionInitial": 0.0002734196348515485
    },
    {
      "teamId": "KSA",
      "name": "Saudi Arabia",
      "code": "KSA",
      "groupId": "H",
      "pWinGroup": 0,
      "pAdvanceGroup": 0,
      "pReachR16": 0,
      "pReachQF": 0,
      "pReachSF": 0,
      "pReachFinal": 0,
      "pChampion": 0,
      "pChampionModel": 0,
      "pChampionInitial": 0.0008
    },
    {
      "teamId": "URU",
      "name": "Uruguay",
      "code": "URU",
      "groupId": "H",
      "pWinGroup": 0,
      "pAdvanceGroup": 0,
      "pReachR16": 0,
      "pReachQF": 0,
      "pReachSF": 0,
      "pReachFinal": 0,
      "pChampion": 0,
      "pChampionModel": 0,
      "pChampionInitial": 0.0188
    },
    {
      "teamId": "FRA",
      "name": "France",
      "code": "FRA",
      "groupId": "I",
      "pWinGroup": 1,
      "pAdvanceGroup": 1,
      "pReachR16": 1,
      "pReachQF": 0.69286,
      "pReachSF": 0.47886,
      "pReachFinal": 0.29254,
      "pChampion": 0.216468883943736,
      "pChampionModel": 0.17484,
      "pChampionMarket": 0.31360294647912007,
      "pChampionInitial": 0.17990088394373602
    },
    {
      "teamId": "SEN",
      "name": "Senegal",
      "code": "SEN",
      "groupId": "I",
      "pWinGroup": 0,
      "pAdvanceGroup": 1,
      "pReachR16": 0,
      "pReachQF": 0,
      "pReachSF": 0,
      "pReachFinal": 0,
      "pChampion": 0,
      "pChampionModel": 0,
      "pChampionInitial": 0.0216
    },
    {
      "teamId": "IRQ",
      "name": "Iraq",
      "code": "IRQ",
      "groupId": "I",
      "pWinGroup": 0,
      "pAdvanceGroup": 0,
      "pReachR16": 0,
      "pReachQF": 0,
      "pReachSF": 0,
      "pReachFinal": 0,
      "pChampion": 0,
      "pChampionModel": 0,
      "pChampionInitial": 0.0006
    },
    {
      "teamId": "NOR",
      "name": "Norway",
      "code": "NOR",
      "groupId": "I",
      "pWinGroup": 0,
      "pAdvanceGroup": 1,
      "pReachR16": 1,
      "pReachQF": 0.281,
      "pReachSF": 0.08814,
      "pReachFinal": 0.03036,
      "pChampion": 0.013087102764295859,
      "pChampionModel": 0.00984,
      "pChampionMarket": 0.020663675880986204,
      "pChampionInitial": 0.008579102764295861
    },
    {
      "teamId": "ARG",
      "name": "Argentina",
      "code": "ARG",
      "groupId": "J",
      "pWinGroup": 1,
      "pAdvanceGroup": 1,
      "pReachR16": 0.9598,
      "pReachQF": 0.75896,
      "pReachSF": 0.53694,
      "pReachFinal": 0.3229,
      "pChampion": 0.18070861824678064,
      "pChampionModel": 0.18454,
      "pChampionMarket": 0.17176872748926889,
      "pChampionInitial": 0.14659061824678066
    },
    {
      "teamId": "ALG",
      "name": "Algeria",
      "code": "ALG",
      "groupId": "J",
      "pWinGroup": 0,
      "pAdvanceGroup": 1,
      "pReachR16": 0.34822,
      "pReachQF": 0.13854,
      "pReachSF": 0.03854,
      "pReachFinal": 0.01198,
      "pChampion": 0.0027060874078865932,
      "pChampionModel": 0.0032,
      "pChampionMarket": 0.001553624692955311,
      "pChampionInitial": 0.0025660874078865933
    },
    {
      "teamId": "AUT",
      "name": "Austria",
      "code": "AUT",
      "groupId": "J",
      "pWinGroup": 0,
      "pAdvanceGroup": 1,
      "pReachR16": 0,
      "pReachQF": 0,
      "pReachSF": 0,
      "pReachFinal": 0,
      "pChampion": 0.0002934610669248085,
      "pChampionModel": 0,
      "pChampionMarket": 0.0009782035564160282,
      "pChampionInitial": 0.004353461066924808
    },
    {
      "teamId": "JOR",
      "name": "Jordan",
      "code": "JOR",
      "groupId": "J",
      "pWinGroup": 0,
      "pAdvanceGroup": 0,
      "pReachR16": 0,
      "pReachQF": 0,
      "pReachSF": 0,
      "pReachFinal": 0,
      "pChampion": 0,
      "pChampionModel": 0,
      "pChampionInitial": 0.0002
    },
    {
      "teamId": "POR",
      "name": "Portugal",
      "code": "POR",
      "groupId": "K",
      "pWinGroup": 0,
      "pAdvanceGroup": 1,
      "pReachR16": 1,
      "pReachQF": 0.3724,
      "pReachSF": 0.19994,
      "pReachFinal": 0.09082,
      "pChampion": 0.044273763892214144,
      "pChampionModel": 0.04092,
      "pChampionMarket": 0.05209921297404716,
      "pChampionInitial": 0.05216976389221415
    },
    {
      "teamId": "COD",
      "name": "Congo DR",
      "code": "COD",
      "groupId": "K",
      "pWinGroup": 0,
      "pAdvanceGroup": 1,
      "pReachR16": 0,
      "pReachQF": 0,
      "pReachSF": 0,
      "pReachFinal": 0,
      "pChampion": 0,
      "pChampionModel": 0,
      "pChampionInitial": 0.001
    },
    {
      "teamId": "UZB",
      "name": "Uzbekistan",
      "code": "UZB",
      "groupId": "K",
      "pWinGroup": 0,
      "pAdvanceGroup": 0,
      "pReachR16": 0,
      "pReachQF": 0,
      "pReachSF": 0,
      "pReachFinal": 0,
      "pChampion": 0,
      "pChampionModel": 0,
      "pChampionInitial": 0.0006
    },
    {
      "teamId": "COL",
      "name": "Colombia",
      "code": "COL",
      "groupId": "K",
      "pWinGroup": 1,
      "pAdvanceGroup": 1,
      "pReachR16": 0.87084,
      "pReachQF": 0.50776,
      "pReachSF": 0.20752,
      "pReachFinal": 0.08932,
      "pChampion": 0.03368083282639967,
      "pChampionModel": 0.0363,
      "pChampionMarket": 0.027569442754665587,
      "pChampionInitial": 0.02647083282639967
    },
    {
      "teamId": "ENG",
      "name": "England",
      "code": "ENG",
      "groupId": "L",
      "pWinGroup": 1,
      "pAdvanceGroup": 1,
      "pReachR16": 1,
      "pReachQF": 0.6025,
      "pReachSF": 0.3611,
      "pReachFinal": 0.19882,
      "pChampion": 0.09686669963613251,
      "pChampionModel": 0.10324,
      "pChampionMarket": 0.08199566545377504,
      "pChampionInitial": 0.08815869963613251
    },
    {
      "teamId": "CRO",
      "name": "Croatia",
      "code": "CRO",
      "groupId": "L",
      "pWinGroup": 0,
      "pAdvanceGroup": 1,
      "pReachR16": 0,
      "pReachQF": 0,
      "pReachSF": 0,
      "pReachFinal": 0,
      "pChampion": 0.0010773867655232158,
      "pChampionModel": 0,
      "pChampionMarket": 0.0035912892184107193,
      "pChampionInitial": 0.019137386765523217
    },
    {
      "teamId": "GHA",
      "name": "Ghana",
      "code": "GHA",
      "groupId": "L",
      "pWinGroup": 0,
      "pAdvanceGroup": 1,
      "pReachR16": 0.12916,
      "pReachQF": 0.0332,
      "pReachSF": 0.00476,
      "pReachFinal": 0.0009,
      "pChampion": 0.000541347753620187,
      "pChampionModel": 0.00008,
      "pChampionMarket": 0.0016178258454006237,
      "pChampionInitial": 0.0004853477536201871
    },
    {
      "teamId": "PAN",
      "name": "Panama",
      "code": "PAN",
      "groupId": "L",
      "pWinGroup": 0,
      "pAdvanceGroup": 0,
      "pReachR16": 0,
      "pReachQF": 0,
      "pReachSF": 0,
      "pReachFinal": 0,
      "pChampion": 0,
      "pChampionModel": 0,
      "pChampionInitial": 0.0024
    }
  ],
  "championDistribution": {
    "MEX": 0.03826,
    "CAN": 0.00666,
    "SUI": 0.016,
    "BRA": 0.08782,
    "USA": 0.02184,
    "AUS": 0.0035,
    "GER": 0.02562,
    "NED": 0.06314,
    "BEL": 0.04576,
    "EGY": 0.00432,
    "ESP": 0.13408,
    "CPV": 0.00004,
    "FRA": 0.17484,
    "NOR": 0.00984,
    "ARG": 0.18454,
    "ALG": 0.0032,
    "POR": 0.04092,
    "COL": 0.0363,
    "ENG": 0.10324,
    "GHA": 0.00008
  },
  "modelConfig": {
    "type": "poisson",
    "baseGoalsRate": 1.25,
    "blendOddsWeight": 0.3,
    "knockoutGoalsMultiplier": 0.85,
    "formVolatility": 0.05,
    "eloRegressionFactor": 1
  },
  "simCount": 50000,
  "seed": 625564635,
  "generatedAt": "2026-07-03T00:03:18.665Z",
  "dataSnapshotTimestamp": "2026-07-03T00:03:12.620Z"
}