{
  "teams": [
    {
      "teamId": "MEX",
      "name": "Mexico",
      "code": "MEX",
      "groupId": "A",
      "pWinGroup": 0.95976,
      "pAdvanceGroup": 1,
      "pReachR16": 0.6596,
      "pReachQF": 0.3141,
      "pReachSF": 0.1613,
      "pReachFinal": 0.07166,
      "pChampion": 0.026979023117601378,
      "pChampionModel": 0.03286,
      "pChampionMarket": 0.013256743725337939,
      "pChampionInitial": 0.02231702311760138
    },
    {
      "teamId": "RSA",
      "name": "South Africa",
      "code": "RSA",
      "groupId": "A",
      "pWinGroup": 0,
      "pAdvanceGroup": 0.14582,
      "pReachR16": 0.05152,
      "pReachQF": 0.01156,
      "pReachSF": 0.0021,
      "pReachFinal": 0.0004,
      "pChampion": 0.0002731876776775117,
      "pChampionModel": 0.00006,
      "pChampionMarket": 0.0007706255922583723,
      "pChampionInitial": 0.0006511876776775117
    },
    {
      "teamId": "KOR",
      "name": "South Korea",
      "code": "KOR",
      "groupId": "A",
      "pWinGroup": 0.04024,
      "pAdvanceGroup": 0.95338,
      "pReachR16": 0.50742,
      "pReachQF": 0.18014,
      "pReachSF": 0.05612,
      "pReachFinal": 0.0212,
      "pChampion": 0.005415902300889716,
      "pChampionModel": 0.00656,
      "pChampionMarket": 0.0027463410029657225,
      "pChampionInitial": 0.006563902300889717
    },
    {
      "teamId": "CZE",
      "name": "Czechia",
      "code": "CZE",
      "groupId": "A",
      "pWinGroup": 0,
      "pAdvanceGroup": 0.15266,
      "pReachR16": 0.05492,
      "pReachQF": 0.01864,
      "pReachSF": 0.00502,
      "pReachFinal": 0.0012,
      "pChampion": 0.000576879299735733,
      "pChampionModel": 0.00024,
      "pChampionMarket": 0.00136293099911911,
      "pChampionInitial": 0.0022288792997357328
    },
    {
      "teamId": "CAN",
      "name": "Canada",
      "code": "CAN",
      "groupId": "B",
      "pWinGroup": 0,
      "pAdvanceGroup": 1,
      "pReachR16": 0.47844,
      "pReachQF": 0.14934,
      "pReachSF": 0.04204,
      "pReachFinal": 0.01306,
      "pChampion": 0.00418738171034564,
      "pChampionModel": 0.004,
      "pChampionMarket": 0.004624605701152136,
      "pChampionInitial": 0.004607381710345641
    },
    {
      "teamId": "BIH",
      "name": "Bosnia-Herzegovina",
      "code": "BIH",
      "groupId": "B",
      "pWinGroup": 0,
      "pAdvanceGroup": 1,
      "pReachR16": 0.22744,
      "pReachQF": 0.06612,
      "pReachSF": 0.01214,
      "pReachFinal": 0.00222,
      "pChampion": 0.0007393350475397961,
      "pChampionModel": 0.00052,
      "pChampionMarket": 0.0012511168251326539,
      "pChampionInitial": 0.000655335047539796
    },
    {
      "teamId": "QAT",
      "name": "Qatar",
      "code": "QAT",
      "groupId": "B",
      "pWinGroup": 0,
      "pAdvanceGroup": 0,
      "pReachR16": 0,
      "pReachQF": 0,
      "pReachSF": 0,
      "pReachFinal": 0,
      "pChampion": 0,
      "pChampionModel": 0,
      "pChampionMarket": 0.000682706026996856,
      "pChampionInitial": 0.0009048118080990568
    },
    {
      "teamId": "SUI",
      "name": "Switzerland",
      "code": "SUI",
      "groupId": "B",
      "pWinGroup": 1,
      "pAdvanceGroup": 1,
      "pReachR16": 0.58136,
      "pReachQF": 0.28116,
      "pReachSF": 0.1048,
      "pReachFinal": 0.04592,
      "pChampion": 0.01539565951898542,
      "pChampionModel": 0.01796,
      "pChampionMarket": 0.009412198396618067,
      "pChampionInitial": 0.014863659518985418
    },
    {
      "teamId": "BRA",
      "name": "Brazil",
      "code": "BRA",
      "groupId": "C",
      "pWinGroup": 0.54624,
      "pAdvanceGroup": 1,
      "pReachR16": 0.5621,
      "pReachQF": 0.3696,
      "pReachSF": 0.18536,
      "pReachFinal": 0.0928,
      "pChampion": 0.0471939757527543,
      "pChampionModel": 0.0454,
      "pChampionMarket": 0.05137991917584767,
      "pChampionInitial": 0.0555939757527543
    },
    {
      "teamId": "MAR",
      "name": "Morocco",
      "code": "MAR",
      "groupId": "C",
      "pWinGroup": 0.44804,
      "pAdvanceGroup": 1,
      "pReachR16": 0.5552,
      "pReachQF": 0.37208,
      "pReachSF": 0.18844,
      "pReachFinal": 0.09518,
      "pChampion": 0.03933586635108774,
      "pChampionModel": 0.04678,
      "pChampionMarket": 0.021966221170292486,
      "pChampionInitial": 0.03962986635108774
    },
    {
      "teamId": "HAI",
      "name": "Haiti",
      "code": "HAI",
      "groupId": "C",
      "pWinGroup": 0,
      "pAdvanceGroup": 0.00204,
      "pReachR16": 0.00022,
      "pReachQF": 0.00002,
      "pReachSF": 0.00002,
      "pReachFinal": 0,
      "pChampion": 0,
      "pChampionModel": 0,
      "pChampionInitial": 0
    },
    {
      "teamId": "SCO",
      "name": "Scotland",
      "code": "SCO",
      "groupId": "C",
      "pWinGroup": 0.00572,
      "pAdvanceGroup": 0.76744,
      "pReachR16": 0.2228,
      "pReachQF": 0.0642,
      "pReachSF": 0.0205,
      "pReachFinal": 0.00478,
      "pChampion": 0.0016080456039355615,
      "pChampionModel": 0.00138,
      "pChampionMarket": 0.002140152013118539,
      "pChampionInitial": 0.0016220456039355616
    },
    {
      "teamId": "USA",
      "name": "United States",
      "code": "USA",
      "groupId": "D",
      "pWinGroup": 0.996,
      "pAdvanceGroup": 1,
      "pReachR16": 0.7718,
      "pReachQF": 0.44558,
      "pReachSF": 0.1944,
      "pReachFinal": 0.08588,
      "pChampion": 0.0344051773557395,
      "pChampionModel": 0.03726,
      "pChampionMarket": 0.027743924519131682,
      "pChampionInitial": 0.021203177355739504
    },
    {
      "teamId": "PAR",
      "name": "Paraguay",
      "code": "PAR",
      "groupId": "D",
      "pWinGroup": 0.00016,
      "pAdvanceGroup": 0.79302,
      "pReachR16": 0.24486,
      "pReachQF": 0.05656,
      "pReachSF": 0.0191,
      "pReachFinal": 0.00602,
      "pChampion": 0.0016943110736912898,
      "pChampionModel": 0.00146,
      "pChampionMarket": 0.0022410369123043,
      "pChampionInitial": 0.00109231107369129
    },
    {
      "teamId": "AUS",
      "name": "Australia",
      "code": "AUS",
      "groupId": "D",
      "pWinGroup": 0.00384,
      "pAdvanceGroup": 0.92946,
      "pReachR16": 0.37436,
      "pReachQF": 0.10378,
      "pReachSF": 0.04104,
      "pReachFinal": 0.01338,
      "pChampion": 0.004180828685212393,
      "pChampionModel": 0.00438,
      "pChampionMarket": 0.003716095617374643,
      "pChampionInitial": 0.005034828685212393
    },
    {
      "teamId": "TUR",
      "name": "Türkiye",
      "code": "TUR",
      "groupId": "D",
      "pWinGroup": 0,
      "pAdvanceGroup": 0.08052,
      "pReachR16": 0.02514,
      "pReachQF": 0.0072,
      "pReachSF": 0.00266,
      "pReachFinal": 0.001,
      "pChampion": 0.00012,
      "pChampionModel": 0.00012,
      "pChampionInitial": 0.0068
    },
    {
      "teamId": "GER",
      "name": "Germany",
      "code": "GER",
      "groupId": "E",
      "pWinGroup": 0.99718,
      "pAdvanceGroup": 1,
      "pReachR16": 0.7011,
      "pReachQF": 0.321,
      "pReachSF": 0.18222,
      "pReachFinal": 0.09258,
      "pChampion": 0.0478124397950017,
      "pChampionModel": 0.04354,
      "pChampionMarket": 0.057781465983339,
      "pChampionInitial": 0.043514439795001705
    },
    {
      "teamId": "CUW",
      "name": "Curaçao",
      "code": "CUW",
      "groupId": "E",
      "pWinGroup": 0,
      "pAdvanceGroup": 0.07346,
      "pReachR16": 0.01452,
      "pReachQF": 0.00224,
      "pReachSF": 0.00028,
      "pReachFinal": 0,
      "pChampion": 0.00020886266972067142,
      "pChampionModel": 0,
      "pChampionMarket": 0.0006962088990689047,
      "pChampionInitial": 0.0004888626697206713
    },
    {
      "teamId": "CIV",
      "name": "Ivory Coast",
      "code": "CIV",
      "groupId": "E",
      "pWinGroup": 0.00282,
      "pAdvanceGroup": 0.97778,
      "pReachR16": 0.40594,
      "pReachQF": 0.13174,
      "pReachSF": 0.04332,
      "pReachFinal": 0.01258,
      "pChampion": 0.004106630973888609,
      "pChampionModel": 0.00358,
      "pChampionMarket": 0.005335436579628698,
      "pChampionInitial": 0.0044006309738886095
    },
    {
      "teamId": "ECU",
      "name": "Ecuador",
      "code": "ECU",
      "groupId": "E",
      "pWinGroup": 0,
      "pAdvanceGroup": 0.16552,
      "pReachR16": 0.06152,
      "pReachQF": 0.02138,
      "pReachSF": 0.0077,
      "pReachFinal": 0.00242,
      "pChampion": 0.0012483046297472513,
      "pChampionModel": 0.00068,
      "pChampionMarket": 0.002574348765824171,
      "pChampionInitial": 0.005392304629747251
    },
    {
      "teamId": "NED",
      "name": "Netherlands",
      "code": "NED",
      "groupId": "F",
      "pWinGroup": 0.68122,
      "pAdvanceGroup": 1,
      "pReachR16": 0.50828,
      "pReachQF": 0.34464,
      "pReachSF": 0.16848,
      "pReachFinal": 0.08428,
      "pChampion": 0.04338895620468403,
      "pChampionModel": 0.03936,
      "pChampionMarket": 0.05278985401561345,
      "pChampionInitial": 0.04005695620468404
    },
    {
      "teamId": "JPN",
      "name": "Japan",
      "code": "JPN",
      "groupId": "F",
      "pWinGroup": 0.28858,
      "pAdvanceGroup": 1,
      "pReachR16": 0.40652,
      "pReachQF": 0.23404,
      "pReachSF": 0.10258,
      "pReachFinal": 0.04334,
      "pChampion": 0.018699906285754492,
      "pChampionModel": 0.01826,
      "pChampionMarket": 0.01972635428584831,
      "pChampionInitial": 0.01459790628575449
    },
    {
      "teamId": "SWE",
      "name": "Sweden",
      "code": "SWE",
      "groupId": "F",
      "pWinGroup": 0.0302,
      "pAdvanceGroup": 0.92598,
      "pReachR16": 0.19982,
      "pReachQF": 0.06948,
      "pReachSF": 0.02266,
      "pReachFinal": 0.00606,
      "pChampion": 0.0020272224629002125,
      "pChampionModel": 0.00138,
      "pChampionMarket": 0.0035374082096673765,
      "pChampionInitial": 0.0017612224629002127
    },
    {
      "teamId": "TUN",
      "name": "Tunisia",
      "code": "TUN",
      "groupId": "F",
      "pWinGroup": 0,
      "pAdvanceGroup": 0.00002,
      "pReachR16": 0.00002,
      "pReachQF": 0,
      "pReachSF": 0,
      "pReachFinal": 0,
      "pChampion": 0,
      "pChampionModel": 0,
      "pChampionInitial": 0.0008
    },
    {
      "teamId": "BEL",
      "name": "Belgium",
      "code": "BEL",
      "groupId": "G",
      "pWinGroup": 0.42308,
      "pAdvanceGroup": 0.97618,
      "pReachR16": 0.62686,
      "pReachQF": 0.29758,
      "pReachSF": 0.1475,
      "pReachFinal": 0.07044,
      "pChampion": 0.026846076166783573,
      "pChampionModel": 0.03172,
      "pChampionMarket": 0.01547358722261192,
      "pChampionInitial": 0.03726207616678358
    },
    {
      "teamId": "EGY",
      "name": "Egypt",
      "code": "EGY",
      "groupId": "G",
      "pWinGroup": 0.47258,
      "pAdvanceGroup": 1,
      "pReachR16": 0.4701,
      "pReachQF": 0.18376,
      "pReachSF": 0.06234,
      "pReachFinal": 0.02004,
      "pChampion": 0.0051412930183712575,
      "pChampionModel": 0.00602,
      "pChampionMarket": 0.003090976727904193,
      "pChampionInitial": 0.0034472930183712574
    },
    {
      "teamId": "IRN",
      "name": "Iran",
      "code": "IRN",
      "groupId": "G",
      "pWinGroup": 0.10434,
      "pAdvanceGroup": 0.64416,
      "pReachR16": 0.31284,
      "pReachQF": 0.11506,
      "pReachSF": 0.04144,
      "pReachFinal": 0.01634,
      "pChampion": 0.004435084699838985,
      "pChampionModel": 0.00588,
      "pChampionMarket": 0.0010636156661299515,
      "pChampionInitial": 0.008159084699838986
    },
    {
      "teamId": "NZL",
      "name": "New Zealand",
      "code": "NZL",
      "groupId": "G",
      "pWinGroup": 0,
      "pAdvanceGroup": 0.02366,
      "pReachR16": 0.00486,
      "pReachQF": 0.00044,
      "pReachSF": 0.00004,
      "pReachFinal": 0,
      "pChampion": 0.00025460912286931004,
      "pChampionModel": 0,
      "pChampionMarket": 0.0008486970762310336,
      "pChampionInitial": 0.00025460912286931004
    },
    {
      "teamId": "ESP",
      "name": "Spain",
      "code": "ESP",
      "groupId": "H",
      "pWinGroup": 0.8862,
      "pAdvanceGroup": 1,
      "pReachR16": 0.72832,
      "pReachQF": 0.4577,
      "pReachSF": 0.31314,
      "pReachFinal": 0.18482,
      "pChampion": 0.11551781683810858,
      "pChampionModel": 0.10608,
      "pChampionMarket": 0.13753938946036195,
      "pChampionInitial": 0.13590181683810856
    },
    {
      "teamId": "CPV",
      "name": "Cape Verde",
      "code": "CPV",
      "groupId": "H",
      "pWinGroup": 0.02452,
      "pAdvanceGroup": 0.64278,
      "pReachR16": 0.08382,
      "pReachQF": 0.02228,
      "pReachSF": 0.00508,
      "pReachFinal": 0.00084,
      "pChampion": 0.0003978401575376894,
      "pChampionModel": 0.00016,
      "pChampionMarket": 0.0009528005251256312,
      "pChampionInitial": 0.00028584015753768937
    },
    {
      "teamId": "KSA",
      "name": "Saudi Arabia",
      "code": "KSA",
      "groupId": "H",
      "pWinGroup": 0,
      "pAdvanceGroup": 0.3631,
      "pReachR16": 0.04832,
      "pReachQF": 0.01458,
      "pReachSF": 0.00402,
      "pReachFinal": 0.00096,
      "pChampion": 0.00043328912244377106,
      "pChampionModel": 0.00018,
      "pChampionMarket": 0.0010242970748125702,
      "pChampionInitial": 0.000587289122443771
    },
    {
      "teamId": "URU",
      "name": "Uruguay",
      "code": "URU",
      "groupId": "H",
      "pWinGroup": 0.08928,
      "pAdvanceGroup": 0.33114,
      "pReachR16": 0.15478,
      "pReachQF": 0.07034,
      "pReachSF": 0.03188,
      "pReachFinal": 0.01222,
      "pChampion": 0.004068258809809881,
      "pChampionModel": 0.00438,
      "pChampionMarket": 0.003340862699366271,
      "pChampionInitial": 0.01234225880980988
    },
    {
      "teamId": "FRA",
      "name": "France",
      "code": "FRA",
      "groupId": "I",
      "pWinGroup": 0.89636,
      "pAdvanceGroup": 1,
      "pReachR16": 0.80184,
      "pReachQF": 0.5431,
      "pReachSF": 0.37132,
      "pReachFinal": 0.23802,
      "pChampion": 0.1527056485104699,
      "pChampionModel": 0.14296,
      "pChampionMarket": 0.17544549503489962,
      "pChampionInitial": 0.14503364851046988
    },
    {
      "teamId": "SEN",
      "name": "Senegal",
      "code": "SEN",
      "groupId": "I",
      "pWinGroup": 0,
      "pAdvanceGroup": 0.68076,
      "pReachR16": 0.28082,
      "pReachQF": 0.13172,
      "pReachSF": 0.05264,
      "pReachFinal": 0.01954,
      "pChampion": 0.006318514067894724,
      "pChampionModel": 0.00692,
      "pChampionMarket": 0.004915046892982415,
      "pChampionInitial": 0.016594514067894726
    },
    {
      "teamId": "IRQ",
      "name": "Iraq",
      "code": "IRQ",
      "groupId": "I",
      "pWinGroup": 0,
      "pAdvanceGroup": 0.03944,
      "pReachR16": 0.00872,
      "pReachQF": 0.00248,
      "pReachSF": 0.00058,
      "pReachFinal": 0.00014,
      "pChampion": 0.0002461626515892232,
      "pChampionModel": 0.00004,
      "pChampionMarket": 0.0007272088386307441,
      "pChampionInitial": 0.0004981626515892232
    },
    {
      "teamId": "NOR",
      "name": "Norway",
      "code": "NOR",
      "groupId": "I",
      "pWinGroup": 0.10364,
      "pAdvanceGroup": 1,
      "pReachR16": 0.56794,
      "pReachQF": 0.21366,
      "pReachSF": 0.08134,
      "pReachFinal": 0.02866,
      "pChampion": 0.014867844275356826,
      "pChampionModel": 0.01012,
      "pChampionMarket": 0.025946147584522756,
      "pChampionInitial": 0.011003844275356826
    },
    {
      "teamId": "ARG",
      "name": "Argentina",
      "code": "ARG",
      "groupId": "J",
      "pWinGroup": 0.99988,
      "pAdvanceGroup": 1,
      "pReachR16": 0.85554,
      "pReachQF": 0.63928,
      "pReachSF": 0.44864,
      "pReachFinal": 0.29092,
      "pChampion": 0.16070906296598325,
      "pChampionModel": 0.17808,
      "pChampionMarket": 0.12017687655327754,
      "pChampionInitial": 0.12803306296598327
    },
    {
      "teamId": "ALG",
      "name": "Algeria",
      "code": "ALG",
      "groupId": "J",
      "pWinGroup": 0,
      "pAdvanceGroup": 0.81802,
      "pReachR16": 0.28106,
      "pReachQF": 0.1114,
      "pReachSF": 0.03658,
      "pReachFinal": 0.0118,
      "pChampion": 0.0027165793887769336,
      "pChampionModel": 0.00326,
      "pChampionMarket": 0.0014485979625897798,
      "pChampionInitial": 0.0029545793887769335
    },
    {
      "teamId": "AUT",
      "name": "Austria",
      "code": "AUT",
      "groupId": "J",
      "pWinGroup": 0.00012,
      "pAdvanceGroup": 0.95352,
      "pReachR16": 0.30226,
      "pReachQF": 0.11886,
      "pReachSF": 0.04742,
      "pReachFinal": 0.01604,
      "pChampion": 0.004915321450987055,
      "pChampionModel": 0.00542,
      "pChampionMarket": 0.003737738169956852,
      "pChampionInitial": 0.005881321450987055
    },
    {
      "teamId": "JOR",
      "name": "Jordan",
      "code": "JOR",
      "groupId": "J",
      "pWinGroup": 0,
      "pAdvanceGroup": 0.005,
      "pReachR16": 0.00106,
      "pReachQF": 0.00034,
      "pReachSF": 0.00006,
      "pReachFinal": 0,
      "pChampion": 0,
      "pChampionModel": 0,
      "pChampionInitial": 0
    },
    {
      "teamId": "POR",
      "name": "Portugal",
      "code": "POR",
      "groupId": "K",
      "pWinGroup": 0.4624,
      "pAdvanceGroup": 1,
      "pReachR16": 0.66854,
      "pReachQF": 0.37538,
      "pReachSF": 0.19528,
      "pReachFinal": 0.09796,
      "pChampion": 0.05736428852147442,
      "pChampionModel": 0.04712,
      "pChampionMarket": 0.08126762840491474,
      "pChampionInitial": 0.056860288521474414
    },
    {
      "teamId": "COD",
      "name": "Congo DR",
      "code": "COD",
      "groupId": "K",
      "pWinGroup": 0,
      "pAdvanceGroup": 0.49492,
      "pReachR16": 0.10188,
      "pReachQF": 0.03176,
      "pReachSF": 0.00924,
      "pReachFinal": 0.0021,
      "pChampion": 0.0005618873254569074,
      "pChampionModel": 0.00038,
      "pChampionMarket": 0.0009862910848563579,
      "pChampionInitial": 0.0005758873254569073
    },
    {
      "teamId": "UZB",
      "name": "Uzbekistan",
      "code": "UZB",
      "groupId": "K",
      "pWinGroup": 0,
      "pAdvanceGroup": 0.07614,
      "pReachR16": 0.01404,
      "pReachQF": 0.00386,
      "pReachSF": 0.00116,
      "pReachFinal": 0.00026,
      "pChampion": 0.0002451967902329086,
      "pChampionModel": 0.00002,
      "pChampionMarket": 0.0007706559674430288,
      "pChampionInitial": 0.0003711967902329086
    },
    {
      "teamId": "COL",
      "name": "Colombia",
      "code": "COL",
      "groupId": "K",
      "pWinGroup": 0.5376,
      "pAdvanceGroup": 1,
      "pReachR16": 0.64752,
      "pReachQF": 0.34386,
      "pReachSF": 0.16168,
      "pReachFinal": 0.07702,
      "pChampion": 0.029745991833825126,
      "pChampionModel": 0.03496,
      "pChampionMarket": 0.017579972779417096,
      "pChampionInitial": 0.021233991833825128
    },
    {
      "teamId": "ENG",
      "name": "England",
      "code": "ENG",
      "groupId": "L",
      "pWinGroup": 0.85214,
      "pAdvanceGroup": 1,
      "pReachR16": 0.74034,
      "pReachQF": 0.47268,
      "pReachSF": 0.29618,
      "pReachFinal": 0.16,
      "pChampion": 0.09452886029569257,
      "pChampionModel": 0.08792,
      "pChampionMarket": 0.10994953431897528,
      "pChampionInitial": 0.09556486029569258
    },
    {
      "teamId": "CRO",
      "name": "Croatia",
      "code": "CRO",
      "groupId": "L",
      "pWinGroup": 0.12114,
      "pAdvanceGroup": 0.98072,
      "pReachR16": 0.48346,
      "pReachQF": 0.23414,
      "pReachSF": 0.11972,
      "pReachFinal": 0.05352,
      "pChampion": 0.017313703129390293,
      "pChampionModel": 0.0221,
      "pChampionMarket": 0.006145677097967644,
      "pChampionInitial": 0.02284370312939029
    },
    {
      "teamId": "GHA",
      "name": "Ghana",
      "code": "GHA",
      "groupId": "L",
      "pWinGroup": 0.02672,
      "pAdvanceGroup": 0.99966,
      "pReachR16": 0.19934,
      "pReachQF": 0.05096,
      "pReachSF": 0.01034,
      "pReachFinal": 0.00238,
      "pChampion": 0.0008999625321146842,
      "pChampionModel": 0.0005,
      "pChampionMarket": 0.0018332084403822808,
      "pChampionInitial": 0.0005499625321146842
    },
    {
      "teamId": "PAN",
      "name": "Panama",
      "code": "PAN",
      "groupId": "L",
      "pWinGroup": 0,
      "pAdvanceGroup": 0.00372,
      "pReachR16": 0.00086,
      "pReachQF": 0.00018,
      "pReachSF": 0.0001,
      "pReachFinal": 0.00002,
      "pChampion": 0,
      "pChampionModel": 0,
      "pChampionInitial": 0.0018
    }
  ],
  "championDistribution": {
    "MEX": 0.03286,
    "RSA": 0.00006,
    "KOR": 0.00656,
    "CZE": 0.00024,
    "CAN": 0.004,
    "BIH": 0.00052,
    "SUI": 0.01796,
    "BRA": 0.0454,
    "MAR": 0.04678,
    "SCO": 0.00138,
    "USA": 0.03726,
    "PAR": 0.00146,
    "AUS": 0.00438,
    "TUR": 0.00012,
    "GER": 0.04354,
    "CIV": 0.00358,
    "ECU": 0.00068,
    "NED": 0.03936,
    "JPN": 0.01826,
    "SWE": 0.00138,
    "BEL": 0.03172,
    "EGY": 0.00602,
    "IRN": 0.00588,
    "ESP": 0.10608,
    "CPV": 0.00016,
    "KSA": 0.00018,
    "URU": 0.00438,
    "FRA": 0.14296,
    "SEN": 0.00692,
    "IRQ": 0.00004,
    "NOR": 0.01012,
    "ARG": 0.17808,
    "ALG": 0.00326,
    "AUT": 0.00542,
    "POR": 0.04712,
    "COD": 0.00038,
    "UZB": 0.00002,
    "COL": 0.03496,
    "ENG": 0.08792,
    "CRO": 0.0221,
    "GHA": 0.0005
  },
  "modelConfig": {
    "type": "poisson",
    "baseGoalsRate": 1.25,
    "blendOddsWeight": 0.3,
    "knockoutGoalsMultiplier": 0.85,
    "formVolatility": 0.05,
    "eloRegressionFactor": 1
  },
  "simCount": 50000,
  "seed": 4221406469,
  "generatedAt": "2026-06-24T21:51:14.757Z",
  "dataSnapshotTimestamp": "2026-06-24T21:51:07.362Z"
}