{
  "timestamp": "2026-06-28T14:55:46.380Z",
  "blendWeight": 0.3,
  "matches": [
    {
      "id": "ESPN-760486",
      "stage": "r32",
      "groupId": null,
      "homeId": "RSA",
      "awayId": "CAN",
      "kickoffUtc": "2026-06-28T19:00Z",
      "homeXg": 0.9115386747130336,
      "awayXg": 1.238462263112859,
      "pHome": 0.2264861719915049,
      "pDraw": 0.3058635930442955,
      "pAway": 0.46765023496419955,
      "marketBlended": true
    },
    {
      "id": "ESPN-760487",
      "stage": "r32",
      "groupId": null,
      "homeId": "BRA",
      "awayId": "JPN",
      "kickoffUtc": "2026-06-29T17:00Z",
      "homeXg": 1.2608770027651268,
      "awayXg": 0.8953341583075015,
      "pHome": 0.47244013908148763,
      "pDraw": 0.3000829046136875,
      "pAway": 0.22747695630482495,
      "marketBlended": true
    },
    {
      "id": "ESPN-760489",
      "stage": "r32",
      "groupId": null,
      "homeId": "GER",
      "awayId": "PAR",
      "kickoffUtc": "2026-06-29T20:30Z",
      "homeXg": 1.4568377455083266,
      "awayXg": 0.7749018402911415,
      "pHome": 0.5786460568277323,
      "pDraw": 0.26314752055560825,
      "pAway": 0.15820642261665943,
      "marketBlended": true
    },
    {
      "id": "ESPN-760488",
      "stage": "r32",
      "groupId": null,
      "homeId": "NED",
      "awayId": "MAR",
      "kickoffUtc": "2026-06-30T01:00Z",
      "homeXg": 1.061031952783116,
      "awayXg": 1.0639700784117274,
      "pHome": 0.3648770519043956,
      "pDraw": 0.3235838321848558,
      "pAway": 0.3115391159107487,
      "marketBlended": true
    },
    {
      "id": "ESPN-760490",
      "stage": "r32",
      "groupId": null,
      "homeId": "CIV",
      "awayId": "NOR",
      "kickoffUtc": "2026-06-30T17:00Z",
      "homeXg": 1.016912490060956,
      "awayXg": 1.110131167660583,
      "pHome": 0.29487579711289397,
      "pDraw": 0.3137808594760167,
      "pAway": 0.39134334341108934,
      "marketBlended": true
    }
  ]
}